mw_aiohttp_babel/__init__.py
mw_aiohttp_babel/locale.py
mw_aiohttp_babel/middlewares.py
mw_aiohttp_babel-0.1.8.dist-info/METADATA
mw_aiohttp_babel-0.1.8.dist-info/WHEEL
mw_aiohttp_babel-0.1.8.dist-info/top_level.txt
mw_aiohttp_babel-0.1.8.dist-info/RECORD
