Metadata-Version: 2.4
Name: mw-aiohttp-babel
Version: 0.1.8
Summary: Babel localisation support for aiohttp,适用maxwin团队的开发框架
Home-page: https://bitbucket.org/maxwin-inc/mw-aiohttp-babel/src
Author: cxhjet
Author-email: cxhjet@qq.com
License: BSD
Keywords: aiohttp locale babel localisation
Requires-Dist: aiohttp
Requires-Dist: babel
Requires-Dist: speaklater
Dynamic: author
Dynamic: author-email
Dynamic: description
Dynamic: home-page
Dynamic: keywords
Dynamic: license
Dynamic: requires-dist
Dynamic: summary
